{
  "exportDate": "2025-09-05 03:13:38",
  "account": "U*****98",
  "date": "2025-02-05",
  "trades": [
    {
      "accountId": "U*****98",
      "tradeID": "7231577446",
      "reportDate": "20250205",
      "tradeDate": "20250205",
      "tradeTime": "",
      "settleDateTarget": "20250206",
      "transactionType": "ExchTrade",
      "exchange": "BEX",
      "quantity": -9.0,
      "tradePrice": 63.86,
      "tradeMoney": -574.74,
      "proceeds": 574.74,
      "taxes": 0.0,
      "ibCommission": 0.0,
      "ibCommissionCurrency": "USD",
      "netCash": 574.74,
      "closePrice": 63.81,
      "openCloseIndicator": "C",
      "notes": "P",
      "cost": -467.415,
      "fifoPnlRealized": 107.325,
      "mtmPnl": 0.45,
      "origTradePrice": 0.0,
      "origTradeDate": "",
      "origTradeID": "",
      "origOrderID": "0",
      "openDateTime": "",
      "assetCategory": "STK",
      "symbol": "ARKK",
      "description": "ARK INNOVATION ETF",
      "conid": "172522644",
      "securityID": "US00214Q1040",
      "securityIDType": "ISIN",
      "cusip": "00214Q104",
      "isin": "US00214Q1040",
      "listingExchange": "ARCA",
      "underlyingConid": "",
      "underlyingSymbol": "ARKK",
      "underlyingSecurityID": "",
      "underlyingListingExchange": "",
      "issuer": "",
      "multiplier": 1.0,
      "strike": 0.0,
      "expiry": "",
      "putCall": "",
      "principalAdjustFactor": 1,
      "pnl": 107.325,
      "commission": 0.0,
      "currency": "USD"
    },
    {
      "accountId": "U*****98",
      "tradeID": "7231577494",
      "reportDate": "20250205",
      "tradeDate": "20250205",
      "tradeTime": "",
      "settleDateTarget": "20250206",
      "transactionType": "ExchTrade",
      "exchange": "IBKR",
      "quantity": -0.6274,
      "tradePrice": 63.86,
      "tradeMoney": -40.065764,
      "proceeds": 40.065764,
      "taxes": 0.0,
      "ibCommission": 0.0,
      "ibCommissionCurrency": "USD",
      "netCash": 40.065764,
      "closePrice": 63.81,
      "openCloseIndicator": "C",
      "notes": "FP;P",
      "cost": -32.584898,
      "fifoPnlRealized": 7.480866,
      "mtmPnl": 0.0314,
      "origTradePrice": 0.0,
      "origTradeDate": "",
      "origTradeID": "",
      "origOrderID": "0",
      "openDateTime": "",
      "assetCategory": "STK",
      "symbol": "ARKK",
      "description": "ARK INNOVATION ETF",
      "conid": "172522644",
      "securityID": "US00214Q1040",
      "securityIDType": "ISIN",
      "cusip": "00214Q104",
      "isin": "US00214Q1040",
      "listingExchange": "ARCA",
      "underlyingConid": "",
      "underlyingSymbol": "ARKK",
      "underlyingSecurityID": "",
      "underlyingListingExchange": "",
      "issuer": "",
      "multiplier": 1.0,
      "strike": 0.0,
      "expiry": "",
      "putCall": "",
      "principalAdjustFactor": 1,
      "pnl": 7.480866,
      "commission": 0.0,
      "currency": "USD"
    },
    {
      "accountId": "U*****98",
      "tradeID": "7231524652",
      "reportDate": "20250205",
      "tradeDate": "20250205",
      "tradeTime": "",
      "settleDateTarget": "20250206",
      "transactionType": "ExchTrade",
      "exchange": "IBKR",
      "quantity": -0.5041,
      "tradePrice": 99.58,
      "tradeMoney": -50.198278,
      "proceeds": 50.198278,
      "taxes": 0.0,
      "ibCommission": 0.0,
      "ibCommissionCurrency": "USD",
      "netCash": 50.198278,
      "closePrice": 99.28,
      "openCloseIndicator": "C",
      "notes": "FP;P",
      "cost": -43.820657,
      "fifoPnlRealized": 6.377621,
      "mtmPnl": 0.1512,
      "origTradePrice": 0.0,
      "origTradeDate": "",
      "origTradeID": "",
      "origOrderID": "0",
      "openDateTime": "",
      "assetCategory": "STK",
      "symbol": "BABA",
      "description": "ALIBABA GROUP HOLDING-SP ADR",
      "conid": "166090175",
      "securityID": "US01609W1027",
      "securityIDType": "ISIN",
      "cusip": "01609W102",
      "isin": "US01609W1027",
      "listingExchange": "NYSE",
      "underlyingConid": "",
      "underlyingSymbol": "BABA",
      "underlyingSecurityID": "",
      "underlyingListingExchange": "",
      "issuer": "",
      "multiplier": 1.0,
      "strike": 0.0,
      "expiry": "",
      "putCall": "",
      "principalAdjustFactor": 1,
      "pnl": 6.377621,
      "commission": 0.0,
      "currency": "USD"
    },
    {
      "accountId": "U*****98",
      "tradeID": "7231524746",
      "reportDate": "20250205",
      "tradeDate": "20250205",
      "tradeTime": "",
      "settleDateTarget": "20250206",
      "transactionType": "ExchTrade",
      "exchange": "DARK",
      "quantity": -11.0,
      "tradePrice": 99.59,
      "tradeMoney": -1095.49,
      "proceeds": 1095.49,
      "taxes": 0.0,
      "ibCommission": 0.0,
      "ibCommissionCurrency": "USD",
      "netCash": 1095.49,
      "closePrice": 99.28,
      "openCloseIndicator": "C",
      "notes": "P",
      "cost": -956.175,
      "fifoPnlRealized": 139.315,
      "mtmPnl": 3.41,
      "origTradePrice": 0.0,
      "origTradeDate": "",
      "origTradeID": "",
      "origOrderID": "0",
      "openDateTime": "",
      "assetCategory": "STK",
      "symbol": "BABA",
      "description": "ALIBABA GROUP HOLDING-SP ADR",
      "conid": "166090175",
      "securityID": "US01609W1027",
      "securityIDType": "ISIN",
      "cusip": "01609W102",
      "isin": "US01609W1027",
      "listingExchange": "NYSE",
      "underlyingConid": "",
      "underlyingSymbol": "BABA",
      "underlyingSecurityID": "",
      "underlyingListingExchange": "",
      "issuer": "",
      "multiplier": 1.0,
      "strike": 0.0,
      "expiry": "",
      "putCall": "",
      "principalAdjustFactor": 1,
      "pnl": 139.315,
      "commission": 0.0,
      "currency": "USD"
    },
    {
      "accountId": "U*****98",
      "tradeID": "7231530258",
      "reportDate": "20250205",
      "tradeDate": "20250205",
      "tradeTime": "",
      "settleDateTarget": "20250206",
      "transactionType": "ExchTrade",
      "exchange": "IBKR",
      "quantity": -0.9359,
      "tradePrice": 39.92,
      "tradeMoney": -37.361128,
      "proceeds": 37.361128,
      "taxes": 0.0,
      "ibCommission": 0.0,
      "ibCommissionCurrency": "USD",
      "netCash": 37.361128,
      "closePrice": 39.81,
      "openCloseIndicator": "C",
      "notes": "FP;P",
      "cost": -34.745288,
      "fifoPnlRealized": 2.615841,
      "mtmPnl": 0.1029,
      "origTradePrice": 0.0,
      "origTradeDate": "",
      "origTradeID": "",
      "origOrderID": "0",
      "openDateTime": "",
      "assetCategory": "STK",
      "symbol": "JD",
      "description": "JD.COM INC-ADR",
      "conid": "152486141",
      "securityID": "US47215P1066",
      "securityIDType": "ISIN",
      "cusip": "47215P106",
      "isin": "US47215P1066",
      "listingExchange": "NASDAQ",
      "underlyingConid": "",
      "underlyingSymbol": "JD",
      "underlyingSecurityID": "",
      "underlyingListingExchange": "",
      "issuer": "",
      "multiplier": 1.0,
      "strike": 0.0,
      "expiry": "",
      "putCall": "",
      "principalAdjustFactor": 1,
      "pnl": 2.615841,
      "commission": 0.0,
      "currency": "USD"
    },
    {
      "accountId": "U*****98",
      "tradeID": "7231530289",
      "reportDate": "20250205",
      "tradeDate": "20250205",
      "tradeTime": "",
      "settleDateTarget": "20250206",
      "transactionType": "ExchTrade",
      "exchange": "ISLAND",
      "quantity": -26.0,
      "tradePrice": 39.92,
      "tradeMoney": -1037.92,
      "proceeds": 1037.92,
      "taxes": 0.0,
      "ibCommission": 0.0,
      "ibCommissionCurrency": "USD",
      "netCash": 1037.92,
      "closePrice": 39.81,
      "openCloseIndicator": "C",
      "notes": "P",
      "cost": -965.25365,
      "fifoPnlRealized": 72.66635,
      "mtmPnl": 2.86,
      "origTradePrice": 0.0,
      "origTradeDate": "",
      "origTradeID": "",
      "origOrderID": "0",
      "openDateTime": "",
      "assetCategory": "STK",
      "symbol": "JD",
      "description": "JD.COM INC-ADR",
      "conid": "152486141",
      "securityID": "US47215P1066",
      "securityIDType": "ISIN",
      "cusip": "47215P106",
      "isin": "US47215P1066",
      "listingExchange": "NASDAQ",
      "underlyingConid": "",
      "underlyingSymbol": "JD",
      "underlyingSecurityID": "",
      "underlyingListingExchange": "",
      "issuer": "",
      "multiplier": 1.0,
      "strike": 0.0,
      "expiry": "",
      "putCall": "",
      "principalAdjustFactor": 1,
      "pnl": 72.66635,
      "commission": 0.0,
      "currency": "USD"
    },
    {
      "accountId": "U*****98",
      "tradeID": "7231527149",
      "reportDate": "20250205",
      "tradeDate": "20250205",
      "tradeTime": "",
      "settleDateTarget": "20250206",
      "transactionType": "ExchTrade",
      "exchange": "ISLAND",
      "quantity": -108.0,
      "tradePrice": 10.12,
      "tradeMoney": -1092.96,
      "proceeds": 1092.96,
      "taxes": 0.0,
      "ibCommission": 0.0,
      "ibCommissionCurrency": "USD",
      "netCash": 1092.96,
      "closePrice": 10.22,
      "openCloseIndicator": "C",
      "notes": "P",
      "cost": -999.54,
      "fifoPnlRealized": 93.42,
      "mtmPnl": -10.8,
      "origTradePrice": 0.0,
      "origTradeDate": "",
      "origTradeID": "",
      "origOrderID": "0",
      "openDateTime": "",
      "assetCategory": "STK",
      "symbol": "WB",
      "description": "WEIBO CORP-SPON ADR",
      "conid": "148782724",
      "securityID": "US9485961018",
      "securityIDType": "ISIN",
      "cusip": "948596101",
      "isin": "US9485961018",
      "listingExchange": "NASDAQ",
      "underlyingConid": "",
      "underlyingSymbol": "WB",
      "underlyingSecurityID": "",
      "underlyingListingExchange": "",
      "issuer": "",
      "multiplier": 1.0,
      "strike": 0.0,
      "expiry": "",
      "putCall": "",
      "principalAdjustFactor": 1,
      "pnl": 93.42,
      "commission": 0.0,
      "currency": "USD"
    },
    {
      "accountId": "U*****98",
      "tradeID": "7231527318",
      "reportDate": "20250205",
      "tradeDate": "20250205",
      "tradeTime": "",
      "settleDateTarget": "20250206",
      "transactionType": "ExchTrade",
      "exchange": "IBKR",
      "quantity": -0.0496,
      "tradePrice": 10.12,
      "tradeMoney": -0.501952,
      "proceeds": 0.501952,
      "taxes": 0.0,
      "ibCommission": 0.0,
      "ibCommissionCurrency": "USD",
      "netCash": 0.501952,
      "closePrice": 10.22,
      "openCloseIndicator": "C",
      "notes": "FP;P",
      "cost": -0.459296,
      "fifoPnlRealized": 0.042656,
      "mtmPnl": -0.005,
      "origTradePrice": 0.0,
      "origTradeDate": "",
      "origTradeID": "",
      "origOrderID": "0",
      "openDateTime": "",
      "assetCategory": "STK",
      "symbol": "WB",
      "description": "WEIBO CORP-SPON ADR",
      "conid": "148782724",
      "securityID": "US9485961018",
      "securityIDType": "ISIN",
      "cusip": "948596101",
      "isin": "US9485961018",
      "listingExchange": "NASDAQ",
      "underlyingConid": "",
      "underlyingSymbol": "WB",
      "underlyingSecurityID": "",
      "underlyingListingExchange": "",
      "issuer": "",
      "multiplier": 1.0,
      "strike": 0.0,
      "expiry": "",
      "putCall": "",
      "principalAdjustFactor": 1,
      "pnl": 0.042656,
      "commission": 0.0,
      "currency": "USD"
    }
  ],
  "summary": {
    "totalTrades": 8,
    "totalPnL": 429.24,
    "totalCommission": 0.0,
    "netPnL": 429.24,
    "winRate": 1.0,
    "winners": 8,
    "losers": 0,
    "symbols": [
      "ARKK",
      "BABA",
      "JD",
      "WB"
    ],
    "assetCategories": {
      "STK": 8
    }
  }
}