{
  "exportDate": "2025-10-19 03:23:43",
  "account": "U*****98",
  "date": "2025-10-15",
  "trades": [
    {
      "accountId": "U*****98",
      "tradeID": "1150309888",
      "reportDate": "20251015",
      "tradeDate": "20251015",
      "tradeTime": "",
      "settleDateTarget": "20251016",
      "transactionType": "ExchTrade",
      "exchange": "CBOT",
      "quantity": -5.0,
      "tradePrice": 46845.0,
      "tradeMoney": -117112.5,
      "proceeds": 117112.5,
      "taxes": 0.0,
      "ibCommission": -3.1,
      "ibCommissionCurrency": "USD",
      "netCash": 879.4,
      "closePrice": 46492.0,
      "openCloseIndicator": "O",
      "notes": "",
      "cost": -117109.4,
      "fifoPnlRealized": 0.0,
      "mtmPnl": 882.5,
      "origTradePrice": 0.0,
      "origTradeDate": "",
      "origTradeID": "",
      "origOrderID": "0",
      "openDateTime": "",
      "assetCategory": "FUT",
      "symbol": "MYMZ5",
      "description": "MYM 19DEC25",
      "conid": "750150151",
      "securityID": "",
      "securityIDType": "",
      "cusip": "",
      "isin": "",
      "listingExchange": "CBOT",
      "underlyingConid": "362688015",
      "underlyingSymbol": "MYM",
      "underlyingSecurityID": "",
      "underlyingListingExchange": "",
      "issuer": "",
      "multiplier": 0.5,
      "strike": 0.0,
      "expiry": "20251219",
      "putCall": "",
      "principalAdjustFactor": 1,
      "pnl": 0.0,
      "commission": 3.1,
      "currency": "USD"
    },
    {
      "accountId": "U*****98",
      "tradeID": "1150339960",
      "reportDate": "20251015",
      "tradeDate": "20251015",
      "tradeTime": "",
      "settleDateTarget": "20251016",
      "transactionType": "ExchTrade",
      "exchange": "CBOT",
      "quantity": 1.0,
      "tradePrice": 46760.0,
      "tradeMoney": 23380.0,
      "proceeds": -23380.0,
      "taxes": 0.0,
      "ibCommission": -0.62,
      "ibCommissionCurrency": "USD",
      "netCash": -134.62,
      "closePrice": 46492.0,
      "openCloseIndicator": "C",
      "notes": "P",
      "cost": 23421.88,
      "fifoPnlRealized": 41.26,
      "mtmPnl": -134.0,
      "origTradePrice": 0.0,
      "origTradeDate": "",
      "origTradeID": "",
      "origOrderID": "0",
      "openDateTime": "",
      "assetCategory": "FUT",
      "symbol": "MYMZ5",
      "description": "MYM 19DEC25",
      "conid": "750150151",
      "securityID": "",
      "securityIDType": "",
      "cusip": "",
      "isin": "",
      "listingExchange": "CBOT",
      "underlyingConid": "362688015",
      "underlyingSymbol": "MYM",
      "underlyingSecurityID": "",
      "underlyingListingExchange": "",
      "issuer": "",
      "multiplier": 0.5,
      "strike": 0.0,
      "expiry": "20251219",
      "putCall": "",
      "principalAdjustFactor": 1,
      "pnl": 41.26,
      "commission": 0.62,
      "currency": "USD"
    },
    {
      "accountId": "U*****98",
      "tradeID": "1150339963",
      "reportDate": "20251015",
      "tradeDate": "20251015",
      "tradeTime": "",
      "settleDateTarget": "20251016",
      "transactionType": "ExchTrade",
      "exchange": "CBOT",
      "quantity": 2.0,
      "tradePrice": 46760.0,
      "tradeMoney": 46760.0,
      "proceeds": -46760.0,
      "taxes": 0.0,
      "ibCommission": -1.24,
      "ibCommissionCurrency": "USD",
      "netCash": -269.24,
      "closePrice": 46492.0,
      "openCloseIndicator": "C",
      "notes": "P",
      "cost": 46843.76,
      "fifoPnlRealized": 82.52,
      "mtmPnl": -268.0,
      "origTradePrice": 0.0,
      "origTradeDate": "",
      "origTradeID": "",
      "origOrderID": "0",
      "openDateTime": "",
      "assetCategory": "FUT",
      "symbol": "MYMZ5",
      "description": "MYM 19DEC25",
      "conid": "750150151",
      "securityID": "",
      "securityIDType": "",
      "cusip": "",
      "isin": "",
      "listingExchange": "CBOT",
      "underlyingConid": "362688015",
      "underlyingSymbol": "MYM",
      "underlyingSecurityID": "",
      "underlyingListingExchange": "",
      "issuer": "",
      "multiplier": 0.5,
      "strike": 0.0,
      "expiry": "20251219",
      "putCall": "",
      "principalAdjustFactor": 1,
      "pnl": 82.52,
      "commission": 1.24,
      "currency": "USD"
    },
    {
      "accountId": "U*****98",
      "tradeID": "1150339968",
      "reportDate": "20251015",
      "tradeDate": "20251015",
      "tradeTime": "",
      "settleDateTarget": "20251016",
      "transactionType": "ExchTrade",
      "exchange": "CBOT",
      "quantity": 1.0,
      "tradePrice": 46760.0,
      "tradeMoney": 23380.0,
      "proceeds": -23380.0,
      "taxes": 0.0,
      "ibCommission": -0.62,
      "ibCommissionCurrency": "USD",
      "netCash": -134.62,
      "closePrice": 46492.0,
      "openCloseIndicator": "C",
      "notes": "P",
      "cost": 23421.88,
      "fifoPnlRealized": 41.26,
      "mtmPnl": -134.0,
      "origTradePrice": 0.0,
      "origTradeDate": "",
      "origTradeID": "",
      "origOrderID": "0",
      "openDateTime": "",
      "assetCategory": "FUT",
      "symbol": "MYMZ5",
      "description": "MYM 19DEC25",
      "conid": "750150151",
      "securityID": "",
      "securityIDType": "",
      "cusip": "",
      "isin": "",
      "listingExchange": "CBOT",
      "underlyingConid": "362688015",
      "underlyingSymbol": "MYM",
      "underlyingSecurityID": "",
      "underlyingListingExchange": "",
      "issuer": "",
      "multiplier": 0.5,
      "strike": 0.0,
      "expiry": "20251219",
      "putCall": "",
      "principalAdjustFactor": 1,
      "pnl": 41.26,
      "commission": 0.62,
      "currency": "USD"
    },
    {
      "accountId": "U*****98",
      "tradeID": "1150339974",
      "reportDate": "20251015",
      "tradeDate": "20251015",
      "tradeTime": "",
      "settleDateTarget": "20251016",
      "transactionType": "ExchTrade",
      "exchange": "CBOT",
      "quantity": 1.0,
      "tradePrice": 46760.0,
      "tradeMoney": 23380.0,
      "proceeds": -23380.0,
      "taxes": 0.0,
      "ibCommission": -0.62,
      "ibCommissionCurrency": "USD",
      "netCash": -134.62,
      "closePrice": 46492.0,
      "openCloseIndicator": "C",
      "notes": "P",
      "cost": 23421.88,
      "fifoPnlRealized": 41.26,
      "mtmPnl": -134.0,
      "origTradePrice": 0.0,
      "origTradeDate": "",
      "origTradeID": "",
      "origOrderID": "0",
      "openDateTime": "",
      "assetCategory": "FUT",
      "symbol": "MYMZ5",
      "description": "MYM 19DEC25",
      "conid": "750150151",
      "securityID": "",
      "securityIDType": "",
      "cusip": "",
      "isin": "",
      "listingExchange": "CBOT",
      "underlyingConid": "362688015",
      "underlyingSymbol": "MYM",
      "underlyingSecurityID": "",
      "underlyingListingExchange": "",
      "issuer": "",
      "multiplier": 0.5,
      "strike": 0.0,
      "expiry": "20251219",
      "putCall": "",
      "principalAdjustFactor": 1,
      "pnl": 41.26,
      "commission": 0.62,
      "currency": "USD"
    }
  ],
  "summary": {
    "totalTrades": 5,
    "totalPnL": 206.3,
    "totalCommission": 6.2,
    "netPnL": 200.1,
    "winRate": 1.0,
    "winners": 4,
    "losers": 0,
    "symbols": [
      "MYMZ5"
    ],
    "assetCategories": {
      "FUT": 5
    }
  }
}